pyvalueobjects/__init__.py
pyvalueobjects/abstract/nullablevalueobject.py
pyvalueobjects/abstract/valueobject.py
pyvalueobjects/dates/isodate.py
pyvalueobjects/errors/ValueObjectError.py
pyvalueobjects/lists/array_list.py
pyvalueobjects/lists/nullable_array_list.py
pyvalueobjects/numbers/int.py
pyvalueobjects/numbers/negative_int.py
pyvalueobjects/numbers/negative_or_zero_int.py
pyvalueobjects/numbers/nullable_int.py
pyvalueobjects/numbers/nullable_negative_int.py
pyvalueobjects/numbers/nullable_negative_or_zero_int.py
pyvalueobjects/numbers/nullable_positive_int.py
pyvalueobjects/numbers/nullable_positive_or_zero_int.py
pyvalueobjects/numbers/positive_int.py
pyvalueobjects/numbers/positive_or_zero_int.py
pyvalueobjects/security/cpe.py
pyvalueobjects/security/cve.py
pyvalueobjects/security/nullable_cpe.py
pyvalueobjects/security/nullable_cve.py
pyvalueobjects/strings/non_empty_string.py
pyvalueobjects/strings/nullable_non_empty_string.py
pyvalueobjects/strings/nullable_string.py
pyvalueobjects/strings/nullable_uuid4.py
pyvalueobjects/strings/string.py
pyvalueobjects/strings/uuid4.py
pyvalueobjects-0.28.1.dist-info/LICENSE
pyvalueobjects-0.28.1.dist-info/METADATA
pyvalueobjects-0.28.1.dist-info/WHEEL
pyvalueobjects-0.28.1.dist-info/top_level.txt
pyvalueobjects-0.28.1.dist-info/RECORD
