Metadata-Version: 2.1
Name: pyvalueobjects
Version: 0.28.1
Summary: A collection of Value Objects to save time by generalizing data type and format validations.
Home-page: https://github.com/jparadadev/python-value-objects
Author: Javier Parada
Author-email: javierparadadev@gmail.com
License: MIT
Project-URL: Bug Tracker, https://github.com/jparadadev/python-value-objects/issues
Keywords: valueobjects,values
Platform: any
Classifier: Programming Language :: Python :: 3.7
Classifier: Programming Language :: Python :: 3.8
Classifier: Programming Language :: Python :: 3.9
Classifier: Programming Language :: Python :: 3.10
Classifier: Programming Language :: Python :: 3.11
Classifier: License :: OSI Approved :: MIT License
Classifier: Operating System :: OS Independent
License-File: LICENSE
